carrot/__init__.py
carrot/amqp.py
carrot/app.py
carrot/connections.py
carrot/fields.py
carrot/models.py
carrot/services.py
carrot/settings.py
carrot/utils.py
carrot/management/__init__.py
carrot/management/commands/__init__.py
carrot/management/commands/carrot.py
carrot/migrations/0001_initial.py
carrot/migrations/0002_auto_20200324_2313.py
carrot/migrations/0003_add_pid_field.py
carrot/migrations/__init__.py
djangocarrot-2.4.0.dist-info/LICENSE
djangocarrot-2.4.0.dist-info/METADATA
djangocarrot-2.4.0.dist-info/WHEEL
djangocarrot-2.4.0.dist-info/top_level.txt
djangocarrot-2.4.0.dist-info/RECORD
