Metadata-Version: 2.1
Name: djangocarrot
Version: 2.4.0
Summary: Carrot -- A simple task Queue for Django.
Home-page: https://github.com/jbowen7/djangocarrot
Author: John Bowen
Author-email: jbowen7@gmail.com
Keywords: django,task,queue
License-File: LICENSE
Requires-Dist: pika
